foma_bindings/__init__.py
foma_bindings/fst/__init__.py
foma_bindings/mtfst/__init__.py
foma_bindings-0.1.11.dist-info/LICENSE.txt
foma_bindings-0.1.11.dist-info/METADATA
foma_bindings-0.1.11.dist-info/WHEEL
foma_bindings-0.1.11.dist-info/top_level.txt
foma_bindings-0.1.11.dist-info/RECORD
