Metadata-Version: 2.1
Name: foma-bindings
Version: 0.1.11
Summary: Python bindings for the foma finite-state technology suite
Home-page: https://github.com/CultureFoundryCA/foma_bindings
Author: CultureFoundry
Author-email: info@culturefoundrystudios.com
License: Apache 2.0
Keywords: foma,xfst,hfst,fst,fsm,mtfst,mtfsm
Platform: UNKNOWN
Classifier: Development Status :: 5 - Production/Stable
Classifier: Environment :: Console
Classifier: Intended Audience :: Developers
Classifier: Topic :: Software Development :: Libraries :: Python Modules
Classifier: License :: OSI Approved :: Apache Software License
Classifier: Operating System :: OS Independent
Classifier: Programming Language :: Python :: 3
Requires-Python: >=3.10, <4
License-File: LICENSE.txt
